arabic_eou/__init__.py
arabic_eou/log.py
arabic_eou/plugin.py
arabic_eou/runner.py
arabic_eou/sdk.py
arabic_eou-0.1.0.dist-info/METADATA
arabic_eou-0.1.0.dist-info/WHEEL
arabic_eou-0.1.0.dist-info/top_level.txt
arabic_eou-0.1.0.dist-info/RECORD
