Metadata-Version: 2.4
Name: arabic_eou
Version: 0.1.0
Summary: Arabic End-of-Utterance detection for LiveKit
Author: Eslam Walid
Requires-Python: >=3.10
Requires-Dist: torch
Requires-Dist: transformers
Requires-Dist: huggingface-hub
Requires-Dist: arabert
Requires-Dist: aiohttp
Requires-Dist: livekit
Dynamic: author
Dynamic: requires-dist
Dynamic: requires-python
Dynamic: summary
